screeningBuilding/configFilesBuilding.py
screeningBuilding/screeningBuildingTabs.py
screeningBuilding/confFiles/ModbusTCP_Map_2021_sept_08.xml
screeningBuilding/confFiles/calculatedVars.csv
screeningBuilding/confFiles/compteurs.csv
screeningBuilding/confFiles/configurationMeteo.csv
screeningBuilding/confFiles/dfInstr.pkl
screeningBuilding/confFiles/predefinedCategories.csv
screeningBuilding/confFiles/screenBuilding-10001-001-ConfigurationPLC.csv
screeningBuilding/confFiles/screeningBuilding_RTuserOrientedVersionning.md
screeningBuilding/confFiles/screeningBuilding_userOrientedVersionning.md
screeningBuilding/confFiles/variables.csv
screeningBuilding/confFiles/variables.ods
screeningBuilding-3.7.2.dist-info/METADATA
screeningBuilding-3.7.2.dist-info/WHEEL
screeningBuilding-3.7.2.dist-info/top_level.txt
screeningBuilding-3.7.2.dist-info/RECORD
