Metadata-Version: 2.1
Name: screeningBuilding
Version: 3.7.2
Summary: Utilities package
Home-page: UNKNOWN
Author: Dorian Drevon
Author-email: drevondorian@gmail.com
License: UNKNOWN
Platform: UNKNOWN
Classifier: Programming Language :: Python :: 3
Classifier: License :: OSI Approved :: MIT License
Classifier: Operating System :: OS Independent
Requires-Python: >=3.8
Requires-Dist: dorianUtilsModulaire (==3.12.5)
Requires-Dist: odfpy (==1.4.1)
